LICENSE.txt
MANIFEST.in
README.rst
package.json
setup.cfg
setup.py
ccxt/__init__.py
ccxt/aax.py
ccxt/aofex.py
ccxt/ascendex.py
ccxt/bequant.py
ccxt/bibox.py
ccxt/bigone.py
ccxt/binance.py
ccxt/binancecoinm.py
ccxt/binanceus.py
ccxt/binanceusdm.py
ccxt/bit2c.py
ccxt/bitbank.py
ccxt/bitbay.py
ccxt/bitbns.py
ccxt/bitcoincom.py
ccxt/bitfinex.py
ccxt/bitfinex2.py
ccxt/bitflyer.py
ccxt/bitforex.py
ccxt/bitget.py
ccxt/bithumb.py
ccxt/bitmart.py
ccxt/bitmex.py
ccxt/bitpanda.py
ccxt/bitso.py
ccxt/bitstamp.py
ccxt/bitstamp1.py
ccxt/bittrex.py
ccxt/bitvavo.py
ccxt/bitz.py
ccxt/bl3p.py
ccxt/braziliex.py
ccxt/btcalpha.py
ccxt/btcbox.py
ccxt/btcmarkets.py
ccxt/btctradeua.py
ccxt/btcturk.py
ccxt/buda.py
ccxt/bw.py
ccxt/bybit.py
ccxt/cdax.py
ccxt/cex.py
ccxt/coinbase.py
ccxt/coinbaseprime.py
ccxt/coinbasepro.py
ccxt/coincheck.py
ccxt/coinegg.py
ccxt/coinex.py
ccxt/coinfalcon.py
ccxt/coinfloor.py
ccxt/coinmarketcap.py
ccxt/coinmate.py
ccxt/coinone.py
ccxt/coinspot.py
ccxt/crex24.py
ccxt/currencycom.py
ccxt/delta.py
ccxt/deribit.py
ccxt/digifinex.py
ccxt/eqonex.py
ccxt/equos.py
ccxt/exmo.py
ccxt/exx.py
ccxt/flowbtc.py
ccxt/ftx.py
ccxt/gateio.py
ccxt/gemini.py
ccxt/gopax.py
ccxt/hbtc.py
ccxt/hitbtc.py
ccxt/hollaex.py
ccxt/huobijp.py
ccxt/huobipro.py
ccxt/idex.py
ccxt/independentreserve.py
ccxt/indodax.py
ccxt/itbit.py
ccxt/kraken.py
ccxt/kucoin.py
ccxt/kuna.py
ccxt/latoken.py
ccxt/lbank.py
ccxt/liquid.py
ccxt/luno.py
ccxt/lykke.py
ccxt/mercado.py
ccxt/mixcoins.py
ccxt/ndax.py
ccxt/novadax.py
ccxt/oceanex.py
ccxt/okcoin.py
ccxt/okex.py
ccxt/okex5.py
ccxt/paymium.py
ccxt/phemex.py
ccxt/poloniex.py
ccxt/probit.py
ccxt/qtrade.py
ccxt/ripio.py
ccxt/stex.py
ccxt/therock.py
ccxt/tidebit.py
ccxt/tidex.py
ccxt/timex.py
ccxt/upbit.py
ccxt/vcc.py
ccxt/wavesexchange.py
ccxt/whitebit.py
ccxt/xena.py
ccxt/yobit.py
ccxt/zaif.py
ccxt/zb.py
ccxt/async_support/__init__.py
ccxt/async_support/aax.py
ccxt/async_support/aofex.py
ccxt/async_support/ascendex.py
ccxt/async_support/bequant.py
scxtbyyyq.egg-info/PKG-INFO
scxtbyyyq.egg-info/SOURCES.txt
scxtbyyyq.egg-info/dependency_links.txt
scxtbyyyq.egg-info/requires.txt
scxtbyyyq.egg-info/top_level.txt