Metadata-Version: 2.1
Name: scxtbyyyq
Version: 1.52.94
Summary: A JavaScript / Python / PHP cryptocurrency trading library with support for 130+ exchanges
Home-page: https://ccxt.trade
Author: Igor Kroitor
Author-email: igor.kroitor@gmail.com
License: MIT
Project-URL: Homepage, https://ccxt.trade
Project-URL: Documentation, https://ccxt.readthedocs.io/en/latest/manual.html
Project-URL: Discord, https://discord.gg/dhzSKYU
Project-URL: Twitter, https://twitter.com/ccxt_official
Project-URL: Funding, https://opencollective.com/ccxt
Keywords: algorithmic,algotrading,altcoin,altcoins,api,arbitrage,real-time,realtime,backtest,backtesting,bitcoin,bot,btc,cny,coin,coins,crypto,cryptocurrency,crypto currency,crypto market,currency,currencies,darkcoin,dash,digital currency,doge,dogecoin,e-commerce,etc,eth,ether,ethereum,exchange,exchanges,eur,framework,invest,investing,investor,library,light,litecoin,ltc,market,market data,markets,merchandise,merchant,minimal,ohlcv,order,orderbook,order book,price,price data,pricefeed,private,pub
Platform: UNKNOWN
Classifier: Development Status :: 4 - Beta
Classifier: Intended Audience :: Developers
Classifier: Intended Audience :: Financial and Insurance Industry
Classifier: Intended Audience :: Information Technology
Classifier: Topic :: Software Development :: Build Tools
Classifier: Topic :: Office/Business :: Financial :: Investment
Classifier: License :: OSI Approved :: MIT License
Classifier: Programming Language :: Python :: 2
Classifier: Programming Language :: Python :: 2.7
Classifier: Programming Language :: Python :: 3
Classifier: Programming Language :: Python :: 3.6
Classifier: Programming Language :: Python :: 3.7
Classifier: Programming Language :: Python :: 3.8
Classifier: Programming Language :: Python :: 3.9
Classifier: Programming Language :: JavaScript
Classifier: Programming Language :: PHP
Classifier: Operating System :: OS Independent
Classifier: Environment :: Console
Provides-Extra: qa
Provides-Extra: doc
